[
  {"tr": "Okul hakkında", "en": "about the school"},
  {"tr": "Okul yüzünden", "en": "because of the school"},
  {"tr": "İş hakkında", "en": "about work"},
  {"tr": "İş yüzünden", "en": "because of work"},
  {"tr": "Ailem hakkında", "en": "about my family"},
  {"tr": "Ailem yüzünden", "en": "because of my family"},
  {"tr": "Müzik hakkında", "en": "about the music"},
  {"tr": "Müzik yüzünden", "en": "because of the music"},
  {"tr": "İşim hakkında", "en": "about my job"},
  {"tr": "Senin işin yüzünden", "en": "because of your job"},
  {"tr": "Hayatım hakkında", "en": "about my life"},
  {"tr": "Hayatım yüzünden", "en": "because of my life"},
  {"tr": "Bu kitap hakkında", "en": "about this book"},
  {"tr": "Bu kitaplar yüzünden", "en": "because of these books"},
  {"tr": "Bu şarkılar yüzünden", "en": "because of these songs"},
  {"tr": "Bu sorunlar hakkında", "en": "about these problems"},
  {"tr": "Bu sorunlar yüzünden", "en": "because of these problems"},
  {"tr": "Sorunlar hakkında", "en": "about problems"},
  {"tr": "Sorunlarım hakkında", "en": "about my problems"},
  {"tr": "Sorunlar yüzünden", "en": "because of problems"},
  {"tr": "Sorunlarım yüzünden", "en": "because of my problems"},
  {"tr": "Yağmur yüzünden", "en": "because of the rain"},
  {"tr": "Kar yüzünden", "en": "because of the snow"},
  {"tr": "Fırtına yüzünden", "en": "because of the storm"},
  {"tr": "Hava yüzünden", "en": "because of the weather"},
  {"tr": "Sis yüzünden", "en": "because of the fog"},
  {"tr": "Yağmurdan sonra", "en": "after the rain"},
  {"tr": "Yağmurdan önce", "en": "before the rain"},
  {"tr": "Yıldızlar yüzünden", "en": "because of the stars"},
  {"tr": "Yıldızlar hakkında", "en": "about the stars"},
  {"tr": "Nisan'ın ardından", "en": "after April"},
  {"tr": "Haziran'la beraber", "en": "with June"},
  {"tr": "Haziran'ın ardından", "en": "after June"},
  {"tr": "Temmuz'un ardından", "en": "after July"},
  {"tr": "Ağustostan önce", "en": "before August"},
  {"tr": "Eylülden önce", "en": "before September"},
  {"tr": "Kasım'dan sonra", "en": "after November"},
  {"tr": "Aralıktan önce", "en": "before December"},
  {"tr": "Pazartesinden önce", "en": "before Monday"},
  {"tr": "Salıdan önce", "en": "before Tuesday"},
  {"tr": "Çarşambadan önce", "en": "before Wednesday"},
  {"tr": "Perşembeden sonra", "en": "after Thursday"},
  {"tr": "Cumadan sonra", "en": "after Friday"},
  {"tr": "Cumartesiden sonra", "en": "after Saturday"},
  {"tr": "Pazardan evvel", "en": "before Sunday"},
  {"tr": "İnsanlar yüzünden", "en": "because of people"},
  {"tr": "İnsanlar hakkında", "en": "about the people"},
  {"tr": "Hayvanlar yüzünden", "en": "because of animals"},
  {"tr": "Hayvanlar hakkında", "en": "about the animals"},
  {"tr": "Çocuklarım hakkında", "en": "about my children"},
  {"tr": "Karım hakkında", "en": "about my wife"},
  {"tr": "Kocam yüzünden", "en": "because of my husband"},
  {"tr": "Halam hakkında", "en": "about my aunt"},
  {"tr": "Dayım yüzünden", "en": "because of my uncle"},
  {"tr": "Tatil yüzünden", "en": "because of the holiday"},
  {"tr": "Doğum günüm yüzünden", "en": "because of my birthday"},
  {"tr": "Sorunlar hakkında", "en": "about the problems"},
  {"tr": "Sorunlar yüzünden", "en": "because of problems"},
  {"tr": "Toplantı yüzünden", "en": "because of the meeting"},
  {"tr": "Arkadaşlarım yüzünden", "en": "because of my friends"},
  {"tr": "Türkiye için", "en": "for Turkey"},
  {"tr": "Türkiye’den", "en": "from Turkey"},
  {"tr": "Türkiye ile", "en": "with Turkey"},
  {"tr": "Türkiye olmadan", "en": "without Turkey"},
  {"tr": "Türkiye’ye", "en": "to Turkey"},
  {"tr": "Türkiye’yi", "en": "Turkey"},
  {"tr": "Türkiye’den önce", "en": "before Turkey"},
  {"tr": "Türkiye’den sonra", "en": "after Turkey"},
  {"tr": "Türkiye hakkında", "en": "about Turkey"},
  {"tr": "Türkiye yüzünden", "en": "because of Turkey"},
  {"tr": "Türkiye’nin", "en": "of Turkey"},
  {"tr": "Gelecek hakkında", "en": "about the future"},
  {"tr": "Geleceğim hakkında", "en": "about my future"},
  {"tr": "Ailem hakkında", "en": "about my family"},
  {"tr": "Çocuklarım ile", "en": "with my children"},
  {"tr": "Bir sorun yüzünden", "en": "because of a problem"},
  {"tr": "Bu sorun yüzünden", "en": "because of this problem"},
  {"tr": "Bu sorunlar hakkında", "en": "about these problems"},
  {"tr": "Ülkem için", "en": "for my country"},
  {"tr": "Evimden", "en": "from my house"},
  {"tr": "Evim olmadan", "en": "without my house"},
  {"tr": "Telefonum olmadan", "en": "without my phone"},
  {"tr": "Telefonum için", "en": "for my phone"},
  {"tr": "Telefonum yüzünden", "en": "because of my phone"},
  {"tr": "Bilgisayarımla", "en": "with my computer"},
  {"tr": "Bilgisayarımın", "en": "of my computer"},
  {"tr": "Bilgisayarım için", "en": "for my computer"},
  {"tr": "Senin Bilgisayarından önce", "en": "before your computer"},
  {"tr": "Bilgisayarın yüzünden", "en": "because of your computer"},
  {"tr": "Restoran için", "en": "for the restaurant"},
  {"tr": "Okulum yüzünden", "en": "because of my school"},
  {"tr": "Bir bardak su için", "en": "for a glass of water"},
  {"tr": "Bir bardak sudan", "en": "from a glass of water"},
  {"tr": "Bir bardak su ile", "en": "with a glass of water"},
  {"tr": "Bir bardak su olmadan", "en": "without a glass of water"},
  {"tr": "Bir bardak su yüzünden", "en": "because of a glass of water"},
  {"tr": "İki bardak su hakkında", "en": "about two glasses of water"},
  {"tr": "Üç arkadaş hakkında", "en": "about three friends"},
  {"tr": "Bahçem yüzünden", "en": "because of my garden"},
  {"tr": "Sebzeler için", "en": "for the vegetables"},
  {"tr": "Sebzeler hakkında", "en": "about the vegetables"},
  {"tr": "Bu sebzeler yüzünden", "en": "because of these vegetables"},
  {"tr": "Sebzelerin", "en": "of the vegetables"},
  {"tr": "Sebzelere", "en": "to the vegetables"},
  {"tr": "Sebzeleri", "en": "the vegetables"},
  {"tr": "Sebzelerimi", "en": "my vegetables"},
  {"tr": "3 sebzeyi", "en": "the three vegetables"},
  {"tr": "5 öğrenciyi", "en": "the five students"},
  {"tr": "10 doktordan", "en": "from ten doctors"},
  {"tr": "7 aileden", "en": "from seven families"},
  {"tr": "7 aileyle", "en": "with seven families"},
  {"tr": "Dört okul için", "en": "for four schools"},
  {"tr": "İki okula", "en": "to two schools"},
  {"tr": "Dört aile için", "en": "for four families"},
  {"tr": "Dört aile yüzünden", "en": "because of four families"},
  {"tr": "Dört aile hakkında", "en": "about four families"},
  {"tr": "Dört aileye", "en": "to four families"},
  {"tr": "Sorunlarım hakkında", "en": "about my problems"},
  {"tr": "Dertlerim hakkında", "en": "about my troubles"},
  {"tr": "Tasalarım hakkında", "en": "about my worries"},
  {"tr": "Problemlerim hakkında", "en": "about my problems"},
  {"tr": "Senin sorunların yüzünden", "en": "because of your problems"},
  {"tr": "Okulum yüzünden", "en": "because of my school"},
  {"tr": "Senin okulun hakkında", "en": "about your school"},
  {"tr": "Bu okullar yüzünden", "en": "because of these schools"},
  {"tr": "Bu öğretmenler yüzünden", "en": "because of these teachers"},
  {"tr": "Üç elma yüzünden", "en": "because of three apples"},
  {"tr": "Bir kilo süt yüzünden", "en": "because of a kilo of milk"},
  {"tr": "Bir doktor yüzünden", "en": "because of a doctor"},
  {"tr": "Bir öğretmen hakkında", "en": "about a teacher"},
  {"tr": "Bu aile için", "en": "for this family"},
  {"tr": "Bu aile hakkında", "en": "about this family"},
  {"tr": "Senin ailenden", "en": "from your family"},
  {"tr": "Benim aileme", "en": "to my family"},
  {"tr": "Benim ailemin", "en": "of my family"},
  {"tr": "Benim ailemden", "en": "from my family"},
  {"tr": "Benim aileme", "en": "to my family"},
  {"tr": "Benim ailemi", "en": "my family"},
  {"tr": "Benim çocuklarımı", "en": "my children"},
  {"tr": "Benim çocuklarımın", "en": "of my children"},
  {"tr": "Benim çocuklarıma", "en": "to my children"},
  {"tr": "Benim çocuklarım için", "en": "for my children"},
  {"tr": "Benim çocuklarım olmadan", "en": "without my children"},
  {"tr": "Benim çocuklarımla", "en": "with my children"},
  {"tr": "Benim çocuklarımdan", "en": "from my children"},
  {"tr": "Benim çocuklarımdan önce", "en": "before my children"},
  {"tr": "Senin çocuklarından sonra", "en": "after your children"},
  {"tr": "Öğlenden önce", "en": "before noon"},
  {"tr": "Öğlenden sonra", "en": "after noon"},
  {"tr": "Akşamdan önce", "en": "before the evening"},
  {"tr": "Akşamdan sonra", "en": "after the evening"},
  {"tr": "Türkiye hakkında", "en": "about Turkey"},
  {"tr": "Amerika yüzünden", "en": "because of America"},
  {"tr": "Almanya için", "en": "for Germany"},
  {"tr": "Çin’den", "en": "from China"},
  {"tr": "Çin için", "en": "for China"},
  {"tr": "Japonyayla", "en": "with Japan"},
  {"tr": "Fransa yüzünden", "en": "because of France"},
  {"tr": "İngiltere hakkında", "en": "about England"}
]
